{
  "dashboard": {
    "id": null,
    "uid": "collector-metrics",
    "title": "Collector Metrics Dashboard",
    "tags": ["collector", "metrics", "prometheus"],
    "timezone": "browser",
    "schemaVersion": 38,
    "version": 0,
    "refresh": "15s",
    "time": {
      "from": "now-1h",
      "to": "now"
    },
    "timepicker": {
      "refresh_intervals": ["5s", "10s", "15s", "30s", "1m", "5m", "15m", "30m", "1h", "2h", "1d"]
    },
    "panels": [
      {
        "id": 1,
        "gridPos": {
          "h": 8,
          "w": 12,
          "x": 0,
          "y": 0
        },
        "type": "timeseries",
        "title": "受信メッセージ数の推移（チャンネル別）",
        "description": "WebSocket から受信したメッセージ数をチャンネル（ticker, orderbooks, trades）別に表示",
        "targets": [
          {
            "datasource": {
              "type": "prometheus",
              "uid": "prometheus"
            },
            "expr": "sum by (channel) (rate(collector_messages_received_total[1m]))",
            "refId": "A",
            "legendFormat": "{{channel}}"
          }
        ],
        "fieldConfig": {
          "defaults": {
            "color": {
              "mode": "palette-classic"
            },
            "custom": {
              "axisLabel": "",
              "axisPlacement": "auto",
              "barAlignment": 0,
              "drawStyle": "line",
              "fillOpacity": 10,
              "gradientMode": "none",
              "hideFrom": {
                "tooltip": false,
                "viz": false,
                "legend": false
              },
              "lineInterpolation": "linear",
              "lineWidth": 1,
              "pointSize": 5,
              "scaleDistribution": {
                "type": "linear"
              },
              "showPoints": "never",
              "spanNulls": false,
              "stacking": {
                "group": "A",
                "mode": "none"
              },
              "thresholdsStyle": {
                "mode": "off"
              }
            },
            "mappings": [],
            "thresholds": {
              "mode": "absolute",
              "steps": [
                {
                  "color": "green",
                  "value": null
                }
              ]
            },
            "unit": "msg/s"
          },
          "overrides": []
        },
        "options": {
          "tooltip": {
            "mode": "multi",
            "sort": "none"
          },
          "legend": {
            "calcs": ["lastNotNull", "max"],
            "displayMode": "table",
            "placement": "bottom",
            "showLegend": true
          }
        }
      },
      {
        "id": 2,
        "gridPos": {
          "h": 8,
          "w": 12,
          "x": 12,
          "y": 0
        },
        "type": "timeseries",
        "title": "配信メッセージ数の推移（ストリーム別）",
        "description": "Redis Stream に配信したメッセージ数をストリーム（md:ticker, md:orderbook, md:trade）別に表示",
        "targets": [
          {
            "datasource": {
              "type": "prometheus",
              "uid": "prometheus"
            },
            "expr": "sum by (stream) (rate(collector_messages_published_total[1m]))",
            "refId": "A",
            "legendFormat": "{{stream}}"
          }
        ],
        "fieldConfig": {
          "defaults": {
            "color": {
              "mode": "palette-classic"
            },
            "custom": {
              "axisLabel": "",
              "axisPlacement": "auto",
              "barAlignment": 0,
              "drawStyle": "line",
              "fillOpacity": 10,
              "gradientMode": "none",
              "hideFrom": {
                "tooltip": false,
                "viz": false,
                "legend": false
              },
              "lineInterpolation": "linear",
              "lineWidth": 1,
              "pointSize": 5,
              "scaleDistribution": {
                "type": "linear"
              },
              "showPoints": "never",
              "spanNulls": false,
              "stacking": {
                "group": "A",
                "mode": "none"
              },
              "thresholdsStyle": {
                "mode": "off"
              }
            },
            "mappings": [],
            "thresholds": {
              "mode": "absolute",
              "steps": [
                {
                  "color": "green",
                  "value": null
                }
              ]
            },
            "unit": "msg/s"
          },
          "overrides": []
        },
        "options": {
          "tooltip": {
            "mode": "multi",
            "sort": "none"
          },
          "legend": {
            "calcs": ["lastNotNull", "max"],
            "displayMode": "table",
            "placement": "bottom",
            "showLegend": true
          }
        }
      },
      {
        "id": 3,
        "gridPos": {
          "h": 8,
          "w": 12,
          "x": 0,
          "y": 8
        },
        "type": "timeseries",
        "title": "エラー発生状況",
        "description": "エラータイプ（api_error, parse_error, publish_error）別のエラー発生率",
        "targets": [
          {
            "datasource": {
              "type": "prometheus",
              "uid": "prometheus"
            },
            "expr": "sum by (error_type) (rate(collector_errors_total[5m]))",
            "refId": "A",
            "legendFormat": "{{error_type}}"
          }
        ],
        "fieldConfig": {
          "defaults": {
            "color": {
              "mode": "palette-classic"
            },
            "custom": {
              "axisLabel": "",
              "axisPlacement": "auto",
              "barAlignment": 0,
              "drawStyle": "line",
              "fillOpacity": 10,
              "gradientMode": "none",
              "hideFrom": {
                "tooltip": false,
                "viz": false,
                "legend": false
              },
              "lineInterpolation": "linear",
              "lineWidth": 1,
              "pointSize": 5,
              "scaleDistribution": {
                "type": "linear"
              },
              "showPoints": "never",
              "spanNulls": false,
              "stacking": {
                "group": "A",
                "mode": "none"
              },
              "thresholdsStyle": {
                "mode": "off"
              }
            },
            "mappings": [],
            "thresholds": {
              "mode": "absolute",
              "steps": [
                {
                  "color": "green",
                  "value": null
                },
                {
                  "color": "red",
                  "value": 0.1
                }
              ]
            },
            "unit": "errors/s"
          },
          "overrides": []
        },
        "options": {
          "tooltip": {
            "mode": "multi",
            "sort": "none"
          },
          "legend": {
            "calcs": ["lastNotNull", "max"],
            "displayMode": "table",
            "placement": "bottom",
            "showLegend": true
          }
        }
      },
      {
        "id": 4,
        "gridPos": {
          "h": 4,
          "w": 6,
          "x": 12,
          "y": 8
        },
        "type": "stat",
        "title": "再接続回数",
        "description": "累計再接続回数",
        "targets": [
          {
            "datasource": {
              "type": "prometheus",
              "uid": "prometheus"
            },
            "expr": "collector_reconnects_total",
            "refId": "A"
          }
        ],
        "fieldConfig": {
          "defaults": {
            "color": {
              "mode": "thresholds"
            },
            "mappings": [],
            "thresholds": {
              "mode": "absolute",
              "steps": [
                {
                  "color": "green",
                  "value": null
                },
                {
                  "color": "yellow",
                  "value": 1
                },
                {
                  "color": "red",
                  "value": 10
                }
              ]
            },
            "unit": "short"
          },
          "overrides": []
        },
        "options": {
          "colorMode": "value",
          "graphMode": "area",
          "justifyMode": "auto",
          "orientation": "auto",
          "reduceOptions": {
            "values": false,
            "calcs": ["lastNotNull"],
            "fields": ""
          },
          "textMode": "auto"
        }
      },
      {
        "id": 5,
        "gridPos": {
          "h": 4,
          "w": 6,
          "x": 18,
          "y": 8
        },
        "type": "stat",
        "title": "総受信メッセージ数",
        "description": "全チャンネルの累計受信メッセージ数",
        "targets": [
          {
            "datasource": {
              "type": "prometheus",
              "uid": "prometheus"
            },
            "expr": "sum(collector_messages_received_total)",
            "refId": "A"
          }
        ],
        "fieldConfig": {
          "defaults": {
            "color": {
              "mode": "thresholds"
            },
            "mappings": [],
            "thresholds": {
              "mode": "absolute",
              "steps": [
                {
                  "color": "green",
                  "value": null
                }
              ]
            },
            "unit": "short"
          },
          "overrides": []
        },
        "options": {
          "colorMode": "value",
          "graphMode": "area",
          "justifyMode": "auto",
          "orientation": "auto",
          "reduceOptions": {
            "values": false,
            "calcs": ["lastNotNull"],
            "fields": ""
          },
          "textMode": "auto"
        }
      },
      {
        "id": 6,
        "gridPos": {
          "h": 8,
          "w": 24,
          "x": 0,
          "y": 12
        },
        "type": "table",
        "title": "メッセージ処理状況",
        "description": "チャンネル/ストリーム別の累計メッセージ数をテーブル形式で表示",
        "targets": [
          {
            "datasource": {
              "type": "prometheus",
              "uid": "prometheus"
            },
            "expr": "collector_messages_received_total",
            "refId": "A",
            "format": "table",
            "instant": true
          },
          {
            "datasource": {
              "type": "prometheus",
              "uid": "prometheus"
            },
            "expr": "collector_messages_published_total",
            "refId": "B",
            "format": "table",
            "instant": true
          }
        ],
        "fieldConfig": {
          "defaults": {
            "custom": {
              "align": "auto",
              "cellOptions": {
                "type": "auto"
              },
              "inspect": false
            },
            "mappings": [],
            "thresholds": {
              "mode": "absolute",
              "steps": [
                {
                  "color": "green",
                  "value": null
                }
              ]
            },
            "unit": "short"
          },
          "overrides": [
            {
              "matcher": {
                "id": "byName",
                "options": "channel"
              },
              "properties": [
                {
                  "id": "custom.width",
                  "value": 150
                }
              ]
            },
            {
              "matcher": {
                "id": "byName",
                "options": "stream"
              },
              "properties": [
                {
                  "id": "custom.width",
                  "value": 200
                }
              ]
            },
            {
              "matcher": {
                "id": "byName",
                "options": "symbol"
              },
              "properties": [
                {
                  "id": "custom.width",
                  "value": 100
                }
              ]
            },
            {
              "matcher": {
                "id": "byName",
                "options": "Value"
              },
              "properties": [
                {
                  "id": "custom.width",
                  "value": 120
                },
                {
                  "id": "custom.align",
                  "value": "right"
                }
              ]
            }
          ]
        },
        "options": {
          "showHeader": true,
          "cellHeight": "sm",
          "footer": {
            "show": false,
            "reducer": ["sum"],
            "countRows": false
          }
        }
      }
    ],
    "editable": true,
    "fiscalYearStartMonth": 0,
    "graphTooltip": 0,
    "links": [],
    "liveNow": false,
    "weekStart": ""
  }
}

